odoo/addons/edi_core_oca/README.rst
odoo/addons/edi_core_oca/__init__.py
odoo/addons/edi_core_oca/__manifest__.py
odoo/addons/edi_core_oca/exceptions.py
odoo/addons/edi_core_oca/hooks.py
odoo/addons/edi_core_oca/utils.py
odoo/addons/edi_core_oca/data/cron.xml
odoo/addons/edi_core_oca/data/edi_configuration.xml
odoo/addons/edi_core_oca/data/ir_actions_server.xml
odoo/addons/edi_core_oca/data/sequence.xml
odoo/addons/edi_core_oca/demo/edi_backend_demo.xml
odoo/addons/edi_core_oca/i18n/edi_core_oca.pot
odoo/addons/edi_core_oca/i18n/edi_oca.pot
odoo/addons/edi_core_oca/i18n/es.po
odoo/addons/edi_core_oca/i18n/fr.po
odoo/addons/edi_core_oca/i18n/it.po
odoo/addons/edi_core_oca/models/__init__.py
odoo/addons/edi_core_oca/models/edi_backend.py
odoo/addons/edi_core_oca/models/edi_backend_type.py
odoo/addons/edi_core_oca/models/edi_configuration.py
odoo/addons/edi_core_oca/models/edi_configuration_trigger.py
odoo/addons/edi_core_oca/models/edi_exchange_consumer_mixin.py
odoo/addons/edi_core_oca/models/edi_exchange_record.py
odoo/addons/edi_core_oca/models/edi_exchange_related_record.py
odoo/addons/edi_core_oca/models/edi_exchange_type.py
odoo/addons/edi_core_oca/models/edi_exchange_type_rule.py
odoo/addons/edi_core_oca/models/edi_id_mixin.py
odoo/addons/edi_core_oca/models/edi_oca_handler.py
odoo/addons/edi_core_oca/models/ir_model.py
odoo/addons/edi_core_oca/readme/CONFIGURE.md
odoo/addons/edi_core_oca/readme/CONTRIBUTORS.md
odoo/addons/edi_core_oca/readme/DESCRIPTION.md
odoo/addons/edi_core_oca/readme/ROADMAP.md
odoo/addons/edi_core_oca/readme/USAGE.md
odoo/addons/edi_core_oca/security/ir_model_access.xml
odoo/addons/edi_core_oca/security/res_groups.xml
odoo/addons/edi_core_oca/static/description/icon.png
odoo/addons/edi_core_oca/static/description/icon.svg
odoo/addons/edi_core_oca/static/description/index.html
odoo/addons/edi_core_oca/static/src/js/widget_edi.esm.js
odoo/addons/edi_core_oca/static/src/xml/widget_edi.xml
odoo_addon_edi_core_oca-18.0.1.5.6.dist-info/METADATA
odoo_addon_edi_core_oca-18.0.1.5.6.dist-info/WHEEL
odoo_addon_edi_core_oca-18.0.1.5.6.dist-info/top_level.txt
odoo_addon_edi_core_oca-18.0.1.5.6.dist-info/RECORD
