Metadata-Version: 2.1
Name: odoo-addon-edi_core_oca
Version: 18.0.1.5.6
Requires-Python: >=3.10
Requires-Dist: PyYAML
Requires-Dist: odoo-addon-base_edi==18.0.*
Requires-Dist: odoo==18.0.*
Requires-Dist: openupgradelib
Summary: Define backends, exchange types, exchange records, basic automation and views for handling EDI exchanges.
Home-page: https://github.com/OCA/edi-framework
License: LGPL-3
Author: ACSONE,Dixmit,Camptocamp,Odoo Community Association (OCA)
Author-email: support@odoo-community.org
Classifier: Programming Language :: Python
Classifier: Framework :: Odoo
Classifier: Framework :: Odoo :: 18.0
Classifier: License :: OSI Approved :: GNU Lesser General Public License v3 (LGPLv3)
Classifier: Development Status :: 4 - Beta
